django_jqgrid/__init__.py
django_jqgrid/admin.py
django_jqgrid/apps.py
django_jqgrid/filters.py
django_jqgrid/mixins.py
django_jqgrid/models.py
django_jqgrid/ordering.py
django_jqgrid/pagination.py
django_jqgrid/serializers.py
django_jqgrid/urls.py
django_jqgrid/utils.py
django_jqgrid/views.py
django_jqgrid/migrations/0001_initial.py
django_jqgrid/migrations/0002_alter_gridfilter_value.py
django_jqgrid/migrations/__init__.py
django_jqgrid/static/django_jqgrid/css/jqgrid-bootstrap.css
django_jqgrid/static/django_jqgrid/js/jqgrid-config.js
django_jqgrid/static/django_jqgrid/js/jqgrid-core.js
django_jqgrid/static/django_jqgrid/js/jqgrid-csrf.js
django_jqgrid/static/django_jqgrid/js/jqgrid-integration.js
django_jqgrid/static/django_jqgrid/js/jqgrid-theme-switcher.js
django_jqgrid/static/django_jqgrid/plugins/jqGrid/css/ui.jqgrid-bootstrap-ui.css
django_jqgrid/static/django_jqgrid/plugins/jqGrid/css/ui.jqgrid-bootstrap.css
django_jqgrid/static/django_jqgrid/plugins/jqGrid/css/ui.jqgrid-bootstrap4.css
django_jqgrid/static/django_jqgrid/plugins/jqGrid/css/ui.jqgrid-bootstrap5.css
django_jqgrid/static/django_jqgrid/plugins/jqGrid/css/ui.jqgrid.css
django_jqgrid/static/django_jqgrid/plugins/jqGrid/css/addons/ui.multiselect.css
django_jqgrid/static/django_jqgrid/plugins/jqGrid/js/grid.aria.js
django_jqgrid/static/django_jqgrid/plugins/jqGrid/js/grid.base.js
django_jqgrid/static/django_jqgrid/plugins/jqGrid/js/grid.celledit.js
django_jqgrid/static/django_jqgrid/plugins/jqGrid/js/grid.common.js
django_jqgrid/static/django_jqgrid/plugins/jqGrid/js/grid.database.js
django_jqgrid/static/django_jqgrid/plugins/jqGrid/js/grid.filter.js
django_jqgrid/static/django_jqgrid/plugins/jqGrid/js/grid.formedit.js
django_jqgrid/static/django_jqgrid/plugins/jqGrid/js/grid.frozenrows.js
django_jqgrid/static/django_jqgrid/plugins/jqGrid/js/grid.grouping.js
django_jqgrid/static/django_jqgrid/plugins/jqGrid/js/grid.inlinedit.js
django_jqgrid/static/django_jqgrid/plugins/jqGrid/js/grid.jqueryui.js
django_jqgrid-1.2.11.dist-info/licenses/LICENSE
django_jqgrid-1.2.11.dist-info/METADATA
django_jqgrid-1.2.11.dist-info/WHEEL
django_jqgrid-1.2.11.dist-info/top_level.txt
django_jqgrid-1.2.11.dist-info/RECORD
