Metadata-Version: 2.4
Name: django-jqgrid
Version: 1.2.11
Summary: A Django app for integrating jqGrid with Django REST Framework
Home-page: https://github.com/coder-aniket/django-jqgrid
Author: Your Name
Author-email: Django jqGrid Team <support@django-jqgrid.org>
License: MIT
Project-URL: Homepage, https://github.com/coder-aniket/django-jqgrid
Project-URL: Bug Reports, https://github.com/coder-aniket/django-jqgrid/issues
Project-URL: Source, https://github.com/coder-aniket/django-jqgrid
Project-URL: Documentation, https://django-jqgrid.readthedocs.io
Keywords: django,jqgrid,rest,framework,grid,datatable
Classifier: Development Status :: 4 - Beta
Classifier: Environment :: Web Environment
Classifier: Framework :: Django
Classifier: Framework :: Django :: 3.2
Classifier: Framework :: Django :: 4.0
Classifier: Framework :: Django :: 4.1
Classifier: Framework :: Django :: 4.2
Classifier: Intended Audience :: Developers
Classifier: License :: OSI Approved :: MIT License
Classifier: Operating System :: OS Independent
Classifier: Programming Language :: Python
Classifier: Programming Language :: Python :: 3
Classifier: Programming Language :: Python :: 3.8
Classifier: Programming Language :: Python :: 3.9
Classifier: Programming Language :: Python :: 3.10
Classifier: Programming Language :: Python :: 3.11
Classifier: Topic :: Internet :: WWW/HTTP
Classifier: Topic :: Internet :: WWW/HTTP :: Dynamic Content
Classifier: Topic :: Software Development :: Libraries :: Application Frameworks
Classifier: Topic :: Software Development :: Libraries :: Python Modules
Requires-Python: >=3.8
License-File: LICENSE
Requires-Dist: Django>=3.2
Requires-Dist: djangorestframework>=3.12.0
Requires-Dist: django-filter>=21.1
Provides-Extra: dev
Requires-Dist: pytest>=6.2; extra == "dev"
Requires-Dist: pytest-django>=4.4; extra == "dev"
Requires-Dist: pytest-cov>=2.12; extra == "dev"
Requires-Dist: black>=21.7b0; extra == "dev"
Requires-Dist: flake8>=3.9; extra == "dev"
Requires-Dist: isort>=5.9; extra == "dev"
Requires-Dist: mypy>=0.910; extra == "dev"
Requires-Dist: django-stubs>=1.9; extra == "dev"
Requires-Dist: djangorestframework-stubs>=1.4; extra == "dev"
Provides-Extra: production
Requires-Dist: redis>=3.5.0; extra == "production"
Requires-Dist: celery>=5.1.0; extra == "production"
Provides-Extra: import-export
Requires-Dist: openpyxl>=3.0.0; extra == "import-export"
Requires-Dist: xlsxwriter>=3.0.0; extra == "import-export"
Requires-Dist: reportlab>=3.6.0; extra == "import-export"
Requires-Dist: Pillow>=8.0.0; extra == "import-export"
Provides-Extra: docs
Requires-Dist: sphinx>=4.0; extra == "docs"
Requires-Dist: sphinx-rtd-theme>=0.5; extra == "docs"
Requires-Dist: recommonmark>=0.7; extra == "docs"
Dynamic: author
Dynamic: home-page
Dynamic: license-file
Dynamic: requires-python
